README.txt
setup.py
pylookwhat/__init__.py
pylookwhat/__main__.py
pylookwhat/lookwhat.py
pylookwhat.egg-info/PKG-INFO
pylookwhat.egg-info/SOURCES.txt
pylookwhat.egg-info/dependency_links.txt
pylookwhat.egg-info/top_level.txt