Metadata-Version: 1.1
Name: pylookwhat
Version: 0.0.3
Summary: look up variables in another python file
Home-page: https://pypi.python.org/pypi/pylookwhat
Author: MaxiL
Author-email: maxil@interserv.com.tw
License: UNKNOWN
Download-URL: https://github.com/maxi119/pylookwhat.git
Platform: UNKNOWN
Classifier: Development Status :: 1 - Planning
Classifier: Intended Audience :: Developers
Classifier: License :: OSI Approved :: Python Software Foundation License
Classifier: Programming Language :: Python
Classifier: Topic :: Utilities
Classifier: Topic :: Software Development :: Libraries :: Python Modules
